setup.py
adic_dist/Binomialdistribution.py
adic_dist/Gaussiandistribution.py
adic_dist/Generaldistribution.py
adic_dist/__init__.py
adic_dist.egg-info/PKG-INFO
adic_dist.egg-info/SOURCES.txt
adic_dist.egg-info/dependency_links.txt
adic_dist.egg-info/not-zip-safe
adic_dist.egg-info/requires.txt
adic_dist.egg-info/top_level.txt