Metadata-Version: 2.1
Name: adic_dist
Version: 1.1
Summary: A package for Gaussian and Binomial distributions
Author: Adithya Chintala
Requires-Dist: matplotlib
